{
  "def_in":"{ %xmm1 %xmm2 }",
  "live_out":"{ %xmm1 }",
  "def_in_formal":"{ %xmm1 %xmm2 }",
  "live_out_formal":"{ %xmm1 }",
  "search_without_uif":false,
  "data":[
    
  ],
  "initial_searches":[
    {
      "success":false,
      "budget":200000,
      "iterations":200000,
      "start_ptime":117
    },
    {
      "success":false,
      "budget":205202,
      "iterations":205202,
      "start_ptime":207
    },
    {
      "success":false,
      "budget":202153,
      "iterations":202153,
      "start_ptime":320
    },
    {
      "success":false,
      "budget":203842,
      "iterations":203842,
      "start_ptime":418
    },
    {
      "success":false,
      "budget":216144,
      "iterations":216144,
      "start_ptime":481
    },
    {
      "success":false,
      "budget":361267,
      "iterations":361267,
      "start_ptime":490
    },
    {
      "success":false,
      "budget":432237,
      "iterations":432237,
      "start_ptime":510
    },
    {
      "success":false,
      "budget":495321,
      "iterations":495321,
      "start_ptime":530
    },
    {
      "success":false,
      "budget":748906,
      "iterations":748906,
      "start_ptime":539
    },
    {
      "success":false,
      "budget":800673,
      "iterations":800673,
      "start_ptime":558
    },
    {
      "success":false,
      "budget":822820,
      "iterations":822820,
      "start_ptime":578
    },
    {
      "success":false,
      "budget":768919,
      "iterations":768919,
      "start_ptime":601
    },
    {
      "success":false,
      "budget":1484678,
      "iterations":1484678,
      "start_ptime":602
    },
    {
      "success":false,
      "budget":1430825,
      "iterations":1430825,
      "start_ptime":622
    },
    {
      "success":false,
      "budget":1836219,
      "iterations":1836219,
      "start_ptime":634
    },
    {
      "success":false,
      "budget":2090155,
      "iterations":2090155,
      "start_ptime":649
    },
    {
      "success":false,
      "budget":3449910,
      "iterations":3449910,
      "start_ptime":654
    },
    {
      "success":false,
      "budget":6899820,
      "iterations":6899820,
      "start_ptime":654
    },
    {
      "success":false,
      "budget":11763542,
      "iterations":11763542,
      "start_ptime":658
    },
    {
      "success":false,
      "budget":17065043,
      "iterations":17065043,
      "start_ptime":666
    },
    {
      "success":false,
      "budget":32781857,
      "iterations":32781857,
      "start_ptime":667
    },
    {
      "success":false,
      "budget":35779499,
      "iterations":35779499,
      "start_ptime":682
    },
    {
      "success":false,
      "budget":25066317,
      "iterations":25066317,
      "start_ptime":708
    },
    {
      "success":false,
      "budget":42656870,
      "iterations":42656870,
      "start_ptime":712
    },
    {
      "success":false,
      "budget":81931703,
      "iterations":81931703,
      "start_ptime":713
    },
    {
      "success":false,
      "budget":100000000,
      "iterations":100000000,
      "start_ptime":715
    },
    {
      "success":false,
      "budget":100000000,
      "iterations":100000000,
      "start_ptime":720
    },
    {
      "success":false,
      "budget":100000000,
      "iterations":100000000,
      "start_ptime":721
    },
    {
      "success":false,
      "budget":100000000,
      "iterations":100000000,
      "start_ptime":741
    },
    {
      "success":false,
      "budget":100000000,
      "iterations":100000000,
      "start_ptime":742
    },
    {
      "success":false,
      "budget":100000000,
      "iterations":100000000,
      "start_ptime":742
    },
    {
      "success":false,
      "budget":100000000,
      "iterations":100000000,
      "start_ptime":742
    }
  ],
  "secondary_searches":[
    
  ],
  "equivalence_classes":{
    "unorderedClasses":[
      
    ]
  }
}