{
  "def_in":"{ %bx }",
  "live_out":"{ %bx %cf %of }",
  "def_in_formal":"{ %bx }",
  "live_out_formal":"{ %bx %cf %of }",
  "search_without_uif":false,
  "data":[
    
  ],
  "initial_searches":[
    {
      "success":false,
      "budget":200000,
      "iterations":200000,
      "start_ptime":162
    },
    {
      "success":false,
      "budget":200330,
      "iterations":200330,
      "start_ptime":320
    },
    {
      "success":false,
      "budget":200687,
      "iterations":200687,
      "start_ptime":460
    },
    {
      "success":false,
      "budget":357888,
      "iterations":357888,
      "start_ptime":466
    },
    {
      "success":false,
      "budget":469597,
      "iterations":469597,
      "start_ptime":482
    },
    {
      "success":false,
      "budget":571025,
      "iterations":571025,
      "start_ptime":499
    },
    {
      "success":false,
      "budget":756103,
      "iterations":756103,
      "start_ptime":512
    },
    {
      "success":false,
      "budget":1409995,
      "iterations":1409995,
      "start_ptime":514
    },
    {
      "success":false,
      "budget":1626142,
      "iterations":1626142,
      "start_ptime":529
    },
    {
      "success":false,
      "budget":2154000,
      "iterations":2154000,
      "start_ptime":540
    },
    {
      "success":false,
      "budget":2625000,
      "iterations":2625000,
      "start_ptime":553
    },
    {
      "success":false,
      "budget":4002134,
      "iterations":4002134,
      "start_ptime":560
    },
    {
      "success":false,
      "budget":5402845,
      "iterations":5402845,
      "start_ptime":570
    },
    {
      "success":false,
      "budget":3895742,
      "iterations":3895742,
      "start_ptime":596
    },
    {
      "success":false,
      "budget":6398421,
      "iterations":6398421,
      "start_ptime":601
    },
    {
      "success":false,
      "budget":11815647,
      "iterations":11815647,
      "start_ptime":603
    },
    {
      "success":false,
      "budget":3162994,
      "iterations":3162994,
      "start_ptime":654
    },
    {
      "success":false,
      "budget":3672549,
      "iterations":3672549,
      "start_ptime":668
    },
    {
      "success":false,
      "budget":1859891,
      "iterations":1859891,
      "start_ptime":704
    },
    {
      "success":false,
      "budget":2546521,
      "iterations":2546521,
      "start_ptime":714
    },
    {
      "success":false,
      "budget":2757602,
      "iterations":2757602,
      "start_ptime":730
    },
    {
      "success":false,
      "budget":4906440,
      "iterations":4906440,
      "start_ptime":733
    },
    {
      "success":false,
      "budget":9812880,
      "iterations":9812880,
      "start_ptime":733
    },
    {
      "success":false,
      "budget":16717393,
      "iterations":16717393,
      "start_ptime":737
    },
    {
      "success":false,
      "budget":27336089,
      "iterations":27336089,
      "start_ptime":742
    },
    {
      "success":false,
      "budget":54672178,
      "iterations":54672178,
      "start_ptime":742
    },
    {
      "success":true,
      "budget":100000000,
      "iterations":81781785,
      "start_ptime":742
    }
  ],
  "secondary_searches":[
    {
      "n_found":0,
      "budget":10000000,
      "iterations":10000000,
      "start_ptime":742
    },
    {
      "n_found":0,
      "budget":10000000,
      "iterations":10000000,
      "start_ptime":742
    },
    {
      "n_found":0,
      "budget":10000000,
      "iterations":10000000,
      "start_ptime":742
    }
  ],
  "equivalence_classes":{
    "unorderedClasses":[
      {
        "programs":[
          {
            "program":"result-00000.s",
            "score":{
              "uif":0,
              "mult":0,
              "nodes":62
            }
          }
        ]
      }
    ]
  }
}