{
  "def_in":"{ %cl %rbx %cf %of }",
  "live_out":"{ %rbx %cf }",
  "def_in_formal":"{ %cl %rbx %cf %of }",
  "live_out_formal":"{ %rbx %cf }",
  "search_without_uif":false,
  "data":[
    
  ],
  "initial_searches":[
    {
      "success":false,
      "budget":200000,
      "iterations":200000,
      "start_ptime":170
    },
    {
      "success":false,
      "budget":212694,
      "iterations":212694,
      "start_ptime":238
    },
    {
      "success":false,
      "budget":384028,
      "iterations":384028,
      "start_ptime":243
    },
    {
      "success":false,
      "budget":355202,
      "iterations":355202,
      "start_ptime":275
    },
    {
      "success":false,
      "budget":216933,
      "iterations":216933,
      "start_ptime":359
    },
    {
      "success":false,
      "budget":203894,
      "iterations":203894,
      "start_ptime":460
    },
    {
      "success":false,
      "budget":327735,
      "iterations":327735,
      "start_ptime":472
    },
    {
      "success":false,
      "budget":571890,
      "iterations":571890,
      "start_ptime":477
    },
    {
      "success":false,
      "budget":804185,
      "iterations":804185,
      "start_ptime":488
    },
    {
      "success":false,
      "budget":401130,
      "iterations":401130,
      "start_ptime":536
    },
    {
      "success":false,
      "budget":378447,
      "iterations":378447,
      "start_ptime":566
    },
    {
      "success":false,
      "budget":447508,
      "iterations":447508,
      "start_ptime":586
    },
    {
      "success":false,
      "budget":840880,
      "iterations":840880,
      "start_ptime":588
    },
    {
      "success":false,
      "budget":1459915,
      "iterations":1459915,
      "start_ptime":592
    },
    {
      "success":false,
      "budget":2013220,
      "iterations":2013220,
      "start_ptime":602
    },
    {
      "success":false,
      "budget":3728391,
      "iterations":3728391,
      "start_ptime":604
    },
    {
      "success":false,
      "budget":1418828,
      "iterations":1418828,
      "start_ptime":648
    },
    {
      "success":false,
      "budget":2732847,
      "iterations":2732847,
      "start_ptime":649
    },
    {
      "success":false,
      "budget":4499421,
      "iterations":4499421,
      "start_ptime":654
    },
    {
      "success":false,
      "budget":7384225,
      "iterations":7384225,
      "start_ptime":659
    },
    {
      "success":false,
      "budget":12095089,
      "iterations":12095089,
      "start_ptime":664
    },
    {
      "success":false,
      "budget":23236916,
      "iterations":23236916,
      "start_ptime":665
    },
    {
      "success":false,
      "budget":9340510,
      "iterations":9340510,
      "start_ptime":705
    },
    {
      "success":false,
      "budget":15289689,
      "iterations":15289689,
      "start_ptime":710
    },
    {
      "success":false,
      "budget":29372239,
      "iterations":29372239,
      "start_ptime":711
    },
    {
      "success":false,
      "budget":56418183,
      "iterations":56418183,
      "start_ptime":712
    },
    {
      "success":false,
      "budget":99935841,
      "iterations":99935841,
      "start_ptime":715
    },
    {
      "success":false,
      "budget":100000000,
      "iterations":100000000,
      "start_ptime":721
    },
    {
      "success":false,
      "budget":100000000,
      "iterations":100000000,
      "start_ptime":730
    },
    {
      "success":false,
      "budget":100000000,
      "iterations":100000000,
      "start_ptime":735
    },
    {
      "success":false,
      "budget":100000000,
      "iterations":100000000,
      "start_ptime":737
    },
    {
      "success":false,
      "budget":100000000,
      "iterations":100000000,
      "start_ptime":738
    },
    {
      "success":false,
      "budget":100000000,
      "iterations":100000000,
      "start_ptime":740
    },
    {
      "success":false,
      "budget":100000000,
      "iterations":100000000,
      "start_ptime":742
    },
    {
      "success":false,
      "budget":100000000,
      "iterations":100000000,
      "start_ptime":742
    },
    {
      "success":false,
      "budget":100000000,
      "iterations":100000000,
      "start_ptime":742
    },
    {
      "success":false,
      "budget":100000000,
      "iterations":100000000,
      "start_ptime":743
    }
  ],
  "secondary_searches":[
    
  ],
  "equivalence_classes":{
    "unorderedClasses":[
      
    ]
  }
}